README.md
setup.py
pulumi_defang/__init__.py
pulumi_defang/_inputs.py
pulumi_defang/_utilities.py
pulumi_defang/outputs.py
pulumi_defang/project.py
pulumi_defang/provider.py
pulumi_defang/pulumi-plugin.json
pulumi_defang/py.typed
pulumi_defang.egg-info/PKG-INFO
pulumi_defang.egg-info/SOURCES.txt
pulumi_defang.egg-info/dependency_links.txt
pulumi_defang.egg-info/not-zip-safe
pulumi_defang.egg-info/requires.txt
pulumi_defang.egg-info/top_level.txt
pulumi_defang/config/__init__.py
pulumi_defang/config/vars.py
pulumi_defang/types/__init__.py
pulumi_defang/types/_inputs.py
pulumi_defang/types/outputs.py