Metadata-Version: 2.1
Name: pulumi-defang
Version: 1.1.0b12
Summary: Take your app from Docker Compose to a secure and scalable cloud deployment with Pulumi.
Home-page: https://github.com/DefangLabs/pulumi-defang
License: Apache-2.0
Project-URL: Repository, https://github.com/DefangLabs/pulumi-defang
Keywords: category/cloud category/infrastructure kind/native defang docker docker compose cloud aws azure gcp digital ocean
Platform: UNKNOWN
Requires-Python: >=3.9
